<?xml version="1.0" encoding="utf-8" ?>
<Buildings>
	<ThingDef ParentName="FurnitureBase"> 
		<defName>CP_AntiFatigueMat</defName>
		<label>anti-fatigue mat</label>
		<description>A rubber mat for colonists to stand on while working. Offers a little comfort, but not as much as a chair. Very easy to clean.</description>
		<graphicData>
			<texPath>Cupro/Object/Furniture/AntiFatigueMat</texPath>
			<graphicClass>Graphic_Single</graphicClass>
		</graphicData>
		<size>(1,1)</size>
		<blockLight>false</blockLight>
		<altitudeLayer>Shadows</altitudeLayer>
		<statBases>
			<MaxHitPoints>300</MaxHitPoints>
			<WorkToMake>50</WorkToMake>
			<Flammability>0.2</Flammability>
			<Beauty>1</Beauty>
			<Cleanliness>5</Cleanliness>
			<Comfort>0.30</Comfort>
		</statBases>
		<CostList>
			<CP_Rubber>10</CP_Rubber>
		</CostList>
		<socialPropernessMatters>false</socialPropernessMatters>
		<rotatable>true</rotatable>
		<pathCost>5</pathCost>
		<passability>Standable</passability>
		<fillPercent>0</fillPercent>
		<constructEffect>ConstructDirt</constructEffect>
		<building>
			<isSittable>true</isSittable>
		</building>
	</ThingDef>
</Buildings>